celery_pantry/__init__.py
celery_pantry/admin.py
celery_pantry/apps.py
celery_pantry/custom_handler.py
celery_pantry/models.py
celery_pantry/monitor_task_events.py
celery_pantry/serializers.py
celery_pantry/settings.py
celery_pantry/views.py
celery_pantry/migrations/0001_initial.py
celery_pantry/migrations/__init__.py
celery_pantry/templates/celery_pantry/tasks_filter.html
celery_pantry-1.1.4.dist-info/LICENSE.txt
celery_pantry-1.1.4.dist-info/METADATA
celery_pantry-1.1.4.dist-info/WHEEL
celery_pantry-1.1.4.dist-info/top_level.txt
celery_pantry-1.1.4.dist-info/zip-safe
celery_pantry-1.1.4.dist-info/RECORD
